README.md
setup.py
ttterminal
tutorterminal/__init__.py
tutorterminal.egg-info/PKG-INFO
tutorterminal.egg-info/SOURCES.txt
tutorterminal.egg-info/dependency_links.txt
tutorterminal.egg-info/requires.txt
tutorterminal.egg-info/top_level.txt