Metadata-Version: 2.1
Name: tutorterminal
Version: 0.2
Summary: A tool to show terminal tutorials.
Home-page: https://github.com/matheusgr/tutorterminal
Author: Matheus Gaudencio
Author-email: matheusgr@gmail.com
License: UNKNOWN
Download-URL: https://github.com/matheusgr/tutorterminal/tarball/master
Platform: UNKNOWN
Classifier: Development Status :: 4 - Beta
Classifier: Programming Language :: Python :: 3
Classifier: License :: OSI Approved :: MIT License
Classifier: Operating System :: OS Independent
Classifier: Topic :: Education :: Computer Aided Instruction (CAI)
Classifier: Topic :: System :: Shells
Classifier: Intended Audience :: Education
Requires-Python: >=3.2
